hello_python/__init__.py
hello_python_derldalfor100-0.2.0.dist-info/LICENSE
hello_python_derldalfor100-0.2.0.dist-info/METADATA
hello_python_derldalfor100-0.2.0.dist-info/WHEEL
hello_python_derldalfor100-0.2.0.dist-info/entry_points.txt
hello_python_derldalfor100-0.2.0.dist-info/top_level.txt
hello_python_derldalfor100-0.2.0.dist-info/RECORD
